{"cameraMode":{"drawMode":0,"name":"Shaded","section":"Shading Mode"},"sceneLighting":true,"audioPlay":false,"sceneViewState":{"m_AlwaysRefresh":false,"showFog":true,"showSkybox":true,"showFlares":true,"showImageEffects":true,"showParticleSystems":true,"showVisualEffectGraphs":true,"m_FxEnabled":true},"in2DMode":false,"pivot":{"x":0.4685923159122467,"y":5.588860988616943,"z":-8.757721900939942},"rotation":{"x":-0.48962050676345827,"y":0.035585083067417148,"z":-0.019758760929107667,"w":-0.8711874485015869},"size":0.8660253882408142,"orthographic":false}